{
  "id": "shippingProcess",
  "name": "Shipping & Delivery Process",
  "type": "PROCESS",
  "extensions": {
    "Process_shippingProcess": {
      "properties": {
        "orderId-id": {
          "id": "orderId-id",
          "name": "orderId",
          "type": "string",
          "required": true,
          "value": ""
        },
        "customerAddress-id": {
          "id": "customerAddress-id",
          "name": "customerAddress",
          "type": "json",
          "required": true,
          "value": {}
        },
        "orderItems-id": {
          "id": "orderItems-id",
          "name": "orderItems",
          "type": "json",
          "required": true,
          "value": []
        },
        "shippingMethod-id": {
          "id": "shippingMethod-id",
          "name": "shippingMethod",
          "type": "string",
          "required": false,
          "value": "STANDARD"
        },
        "selectedShippingMethod-id": {
          "id": "selectedShippingMethod-id",
          "name": "selectedShippingMethod",
          "type": "string",
          "required": false,
          "value": "STANDARD"
        },
        "packageDetails-id": {
          "id": "packageDetails-id",
          "name": "packageDetails",
          "type": "json",
          "required": false,
          "value": {}
        },
        "shippingLabel-id": {
          "id": "shippingLabel-id",
          "name": "shippingLabel",
          "type": "string",
          "required": false,
          "value": ""
        },
        "trackingNumber-id": {
          "id": "trackingNumber-id",
          "name": "trackingNumber",
          "type": "string",
          "required": false,
          "value": ""
        },
        "shippingStatus-id": {
          "id": "shippingStatus-id",
          "name": "shippingStatus",
          "type": "string",
          "required": false,
          "value": "NOT_SHIPPED"
        },
        "deliveryDate-id": {
          "id": "deliveryDate-id",
          "name": "deliveryDate",
          "type": "date",
          "required": false,
          "value": null
        },
        "pickupScheduled-id": {
          "id": "pickupScheduled-id",
          "name": "pickupScheduled",
          "type": "boolean",
          "required": false,
          "value": false
        },
        "customerNotified-id": {
          "id": "customerNotified-id",
          "name": "customerNotified",
          "type": "boolean",
          "required": false,
          "value": false
        }
      },
      "mappings": {
        "prepareShipmentTask": {
          "inputs": {
            "orderId": {
              "type": "variable",
              "value": "orderId"
            },
            "customerAddress": {
              "type": "variable",
              "value": "customerAddress"
            },
            "orderItems": {
              "type": "variable",
              "value": "orderItems"
            },
            "shippingMethod": {
              "type": "variable",
              "value": "selectedShippingMethod"
            }
          },
          "outputs": {
            "packageDetails": {
              "type": "variable",
              "value": "packageInfo"
            },
            "preparedDate": {
              "type": "variable",
              "value": "preparationDate"
            }
          }
        },
        "generateShippingLabelTask": {
          "inputs": {
            "orderId": {
              "type": "variable",
              "value": "orderId"
            },
            "customerAddress": {
              "type": "variable",
              "value": "customerAddress"
            },
            "packageDetails": {
              "type": "variable",
              "value": "packageDetails"
            },
            "shippingMethod": {
              "type": "variable",
              "value": "selectedShippingMethod"
            }
          },
          "outputs": {
            "shippingLabel": {
              "type": "variable",
              "value": "labelUrl"
            },
            "trackingNumber": {
              "type": "variable",
              "value": "trackingId"
            }
          }
        },
        "schedulePriorityPickupTask": {
          "inputs": {
            "orderId": {
              "type": "variable",
              "value": "orderId"
            },
            "trackingNumber": {
              "type": "variable",
              "value": "trackingNumber"
            },
            "packageDetails": {
              "type": "variable",
              "value": "packageDetails"
            },
            "pickupType": {
              "type": "value",
              "value": "PRIORITY"
            }
          },
          "outputs": {
            "pickupScheduled": {
              "type": "variable",
              "value": "scheduled"
            },
            "pickupTime": {
              "type": "variable",
              "value": "scheduledTime"
            },
            "shippingStatus": {
              "type": "variable",
              "value": "IN_TRANSIT"
            }
          }
        },
        "scheduleRegularPickupTask": {
          "inputs": {
            "orderId": {
              "type": "variable",
              "value": "orderId"
            },
            "trackingNumber": {
              "type": "variable",
              "value": "trackingNumber"
            },
            "packageDetails": {
              "type": "variable",
              "value": "packageDetails"
            },
            "pickupType": {
              "type": "value",
              "value": "STANDARD"
            }
          },
          "outputs": {
            "pickupScheduled": {
              "type": "variable",
              "value": "scheduled"
            },
            "pickupTime": {
              "type": "variable",
              "value": "scheduledTime"
            },
            "shippingStatus": {
              "type": "variable",
              "value": "IN_TRANSIT"
            }
          }
        },
        "notifyStorePickupTask": {
          "inputs": {
            "orderId": {
              "type": "variable",
              "value": "orderId"
            },
            "customerEmail": {
              "type": "variable",
              "value": "customerEmail"
            },
            "storeLocation": {
              "type": "variable",
              "value": "pickupLocation"
            }
          },
          "outputs": {
            "customerNotified": {
              "type": "variable",
              "value": "notified"
            },
            "shippingStatus": {
              "type": "variable",
              "value": "READY_FOR_PICKUP"
            }
          }
        },
        "updateTrackingSystemTask": {
          "inputs": {
            "orderId": {
              "type": "variable",
              "value": "orderId"
            },
            "trackingNumber": {
              "type": "variable",
              "value": "trackingNumber"
            },
            "shippingStatus": {
              "type": "variable",
              "value": "shippingStatus"
            },
            "pickupTime": {
              "type": "variable",
              "value": "pickupTime"
            }
          },
          "outputs": {
            "trackingUpdated": {
              "type": "variable",
              "value": "updated"
            }
          }
        },
        "sendDeliveryConfirmationTask": {
          "inputs": {
            "orderId": {
              "type": "variable",
              "value": "orderId"
            },
            "customerEmail": {
              "type": "variable",
              "value": "customerEmail"
            },
            "trackingNumber": {
              "type": "variable",
              "value": "trackingNumber"
            },
            "deliveryDate": {
              "type": "variable",
              "value": "deliveryDate"
            },
            "emailTemplate": {
              "type": "value",
              "value": "delivery_confirmation"
            }
          },
          "outputs": {
            "confirmationSent": {
              "type": "variable",
              "value": "sent"
            },
            "shippingStatus": {
              "type": "variable",
              "value": "DELIVERED"
            }
          }
        }
      },
      "constants": {
        "generateShippingLabelTask": {
          "shippingProvider": {
            "value": "fedex"
          },
          "labelApi": {
            "value": "https://api.fedex.com/label/v1"
          },
          "labelFormat": {
            "value": "PDF"
          }
        },
        "schedulePriorityPickupTask": {
          "priorityService": {
            "value": "OVERNIGHT"
          },
          "pickupApi": {
            "value": "https://api.fedex.com/pickup/v1"
          },
          "maxPickupTime": {
            "value": "PT4H"
          }
        },
        "scheduleRegularPickupTask": {
          "standardService": {
            "value": "GROUND"
          },
          "pickupApi": {
            "value": "https://api.fedex.com/pickup/v1"
          },
          "maxPickupTime": {
            "value": "P1D"
          }
        },
        "updateTrackingSystemTask": {
          "trackingApi": {
            "value": "https://api.fedex.com/tracking/v1"
          },
          "updateFrequency": {
            "value": "PT1H"
          }
        },
        "sendDeliveryConfirmationTask": {
          "smtpServer": {
            "value": "smtp.company.com"
          },
          "fromAddress": {
            "value": "shipping@company.com"
          },
          "emailTemplate": {
            "value": "delivery_confirmation"
          }
        }
      }
    }
  }
}
